click_didyoumean/__init__.py
click_didyoumean-0.2.0.dist-info/LICENSE
click_didyoumean-0.2.0.dist-info/WHEEL
click_didyoumean-0.2.0.dist-info/METADATA
click_didyoumean-0.2.0.dist-info/RECORD
